probabilistic_piping/__init__.py
probabilistic_piping/piping_equations.py
probabilistic_piping/piping_settings.py
probabilistic_piping/probabilistic_base.py
probabilistic_piping/probabilistic_fixedwl.py
probabilistic_piping/probabilistic_io.py
probabilistic_piping-0.0.5.dist-info/METADATA
probabilistic_piping-0.0.5.dist-info/WHEEL
probabilistic_piping-0.0.5.dist-info/RECORD
