Metadata-Version: 2.4
Name: probabilistic_piping
Version: 0.0.5
Summary: Python package for probabilistic piping calculations
Project-URL: Documentation, https://hkv-products-services.github.io/probabilistic_piping
Project-URL: Source, https://github.com/HKV-products-services/probabilistic_piping
Author: Guy Dupuits, Robin Nicolai, Joost Pol, David Haasnoot
License: GNU-GPL V3
Requires-Dist: numpy
Requires-Dist: openturns>=1.23
Requires-Dist: pandas
Requires-Dist: tqdm
